traintrack/__init__.py
traintrack/client.py
traintrack/credentials.py
traintrack/datasets.py
traintrack/instance_config.py
traintrack/models.py
traintrack/oauth_client_config.py
traintrack_mlops-0.0.1.post2.dist-info/METADATA
traintrack_mlops-0.0.1.post2.dist-info/WHEEL
traintrack_mlops-0.0.1.post2.dist-info/top_level.txt
traintrack_mlops-0.0.1.post2.dist-info/RECORD
