Metadata-Version: 2.4
Name: traintrack-mlops
Version: 0.0.1.post2
Summary: Traintrack is a modular MLOps platform designed to manage and monitor the full lifecycle of machine learning workflows — from dataset tracking to deployment — with a robust Go-based backend and an easy-to-use Python SDK.
Requires-Dist: requests
Requires-Dist: pandas
Requires-Dist: pytest
Requires-Dist: joblib
Requires-Dist: requests_oauthlib
Requires-Dist: oauthlib
Dynamic: description
Dynamic: description-content-type
Dynamic: requires-dist
Dynamic: summary
